lexsetAPI/LexsetManager.py
lexsetAPI/__init__.py
lexsetAPI/credentials.py
lexsetAPI-3.5.0.dist-info/METADATA
lexsetAPI-3.5.0.dist-info/WHEEL
lexsetAPI-3.5.0.dist-info/top_level.txt
lexsetAPI-3.5.0.dist-info/RECORD
