Metadata-Version: 2.1
Name: lexsetAPI
Version: 3.5.0
Author: F. Bitonti
Author-email: Francis@lexset.ai
License: Apache 2.0
Classifier: Development Status :: 4 - Beta
Classifier: Programming Language :: Python :: 3
Requires-Dist: pyjson
Requires-Dist: PyYAML
Requires-Dist: pyBase64
Requires-Dist: tqdm
Requires-Dist: requests
